{
  "team": [
    {
      "id": "Ш.Е.Л.15.12.1986",
      "fam": "Шпинева",
      "name": "Евгения",
      "otch": "Леонидовна",
      "position": "Директор",
      "tel": "+375296654556",
      "email": "evgeniya_sobal@gmail.com",
      "dateOfBirth": "15.12.1986",
      "address": "г.Минск, ул.Мястровская, 5, кв.56",
      "photoURL": "img/ceo3.jpg"
    },
    {
      "id": "Ш.Д.А.04.02.1992",
      "fam": "Шпинев",
      "name": "Дмитрий",
      "otch": "Алексеевич",
      "position": "Зам. директора по коммерческим вопросам",
      "tel": "+375296941821",
      "email": "dmitryshpinev@mail.ru",
      "dateOfBirth": "04.02.1992",
      "address": "г.Минск, ул.Мястровская, 5, кв.56",
      "photoURL": "img/fd.jpg"
    },
    {
      "id": "П.М.В.13.03.1990",
      "fam": "Петлицкий",
      "name": "Максим",
      "otch": "Владимирович",
      "position": "Главный инженер",
      "tel": "+375447409315",
      "email": "petlitskiy1990@gmail.com",
      "dateOfBirth": "13.03.1990",
      "address": "г.Минск, ул.Жиновича, 11, кв.29",
      "photoURL": "img/ce3.jpg"
    },
    {
      "id": "С.Е.В.11.01.1971",
      "fam": "Савенкова",
      "name": "Елена",
      "otch": "Викторовна",
      "position": "Главный бухгалтер",
      "tel": "+375296594202",
      "email": "elenasavenkova@gmail.com",
      "dateOfBirth": "11.01.1971",
      "address": "Минская обл., пос.Ратомка, пер.Подгорный, 7",
      "photoURL": "img/ca.jpg"
    },
    {
      "id": "С.Н.В.18.06.1997",
      "fam": "Савенкова",
      "name": "Надежда",
      "otch": "Владимировна",
      "position": "Бухгалтер",
      "tel": "+37529359402",
      "email": "nadyasavenkova@gmail.com",
      "dateOfBirth": "18.06.1997",
      "address": "Минская обл., пос.Ратомка, ер.Подгорный, 7",
      "photoURL": "img/accountant.jpg"
    },
    {
      "id": "Г.А.С.17.07.1995",
      "fam": "Гриневский",
      "name": "Артем",
      "otch": "Сергеевич",
      "position": "Инженер-механик",
      "tel": "+375335629085",
      "email": "agrinevsky@mail.ru",
      "dateOfBirth": "17.07.1995",
      "address": "г.Минск, ул.Бакинская, 6, кв.74",
      "photoURL": "img/im.jpg"
    },
    {
      "id": "М.В.А.30.05.1984",
      "fam": "Мороз",
      "name": "Вячеслав",
      "otch": "Александрович",
      "position": "Монтажник СВиК ",
      "tel": "+375337605511",
      "email": "morozva@tut.by",
      "dateOfBirth": "30.05.1984",
      "address": "г.Минск, ул.Гвардейская, 1А, кв.36",
      "photoURL": "img/mounter_2.jpg"
    },
    {
      "id": "Ш.А.В.16.05.1993",
      "fam": "Шавлюга",
      "name": "Александр",
      "otch": "Викторович",
      "position": "Монтажник СВиК ",
      "tel": "+375298906190",
      "email": "a_shavluga@gmail.com",
      "dateOfBirth": "16.05.1993",
      "address": "г.Минск, ул.Горецкого, 15, кв.71",
      "photoURL": "img/mounter_3.jpg"
    },
    {
      "id": "Ш.Р.В.20.10.1997",
      "fam": "Шишков",
      "name": "Руслан",
      "otch": "Вячеславович",
      "position": "Монтажник СВиК ",
      "tel": "+375295068580",
      "email": "shiskovruslan@tut.by",
      "dateOfBirth": "20.10.1997",
      "address": "Минская обл., г.п.Руденск, ул.Советская, 34, кв.10",
      "photoURL": "img/mounter_1.jpg"
    }
  ],
  "projects": [
    {
      "id": "Time в ТРЦ Галерея",
      "projectName": "Time в ТРЦ Галерея",
      "pCompleted": false,
      "projectTasks": [
        {
          "id": "Time_0",
          "taskName": "монтаж воздуховодов",
          "tCompleted": true,
          "createDate": "01.03.2019",
          "completeDate": "10.03.2019",
          "respPerson": "Гриневский А.С.",
          "factDate": "12.05.2019"
        },
        {
          "id": "Time_1",
          "taskName": "утепление ветки притока",
          "tCompleted": true,
          "createDate": "01.03.2019",
          "completeDate": "10.03.2019",
          "respPerson": "Гриневский А.С."
        },
        {
          "id": "Time_3",
          "taskName": "установка фанкойлов",
          "tCompleted": true,
          "createDate": "01.03.2019",
          "completeDate": "13.03.2019",
          "respPerson": "Мороз В.А.",
          "factDate": "12.05.2019"
        },
        {
          "id": "Time_4",
          "taskName": "обвязка фанкойлов",
          "tCompleted": false,
          "createDate": "01.03.2019",
          "completeDate": "13.03.2019",
          "respPerson": "Мороз В.А."
        },
        {
          "id": "Time_5",
          "taskName": "прокладка воздуховодов от фанкойлов",
          "tCompleted": false,
          "createDate": "01.03.2019",
          "completeDate": "11.03.2019",
          "respPerson": "Шишков Р.В."
        },
        {
          "id": "Time_6",
          "taskName": "установка адаптеров и вентрешеток",
          "tCompleted": false,
          "createDate": "01.03.2019",
          "completeDate": "11.03.2019",
          "respPerson": "Гриневский А.С."
        },
        {
          "id": "Time_7",
          "taskName": "установка и подключение пультов ДУ",
          "tCompleted": false,
          "createDate": "01.03.2019",
          "completeDate": "15.03.2019",
          "respPerson": "Шишков Р.В."
        },
        {
          "id": "Time_8",
          "taskName": "запуск системы чиллер-фанкойла",
          "tCompleted": false,
          "createDate": "01.03.2019",
          "completeDate": "15.03.2019",
          "respPerson": "Шавлюга А.В."
        }
      ]
    },
    {
      "id": "Лукойл",
      "projectName": "Лукойл",
      "pCompleted": false,
      "projectTasks": [
        {
          "id": "Лукойл_0",
          "taskName": "демонтаж существующей VRF-системы",
          "tCompleted": false,
          "createDate": "01.03.2019",
          "completeDate": "13.03.2019",
          "factDate": "07.03.2019",
          "respPerson": "Шавлюга А.В."
        },
        {
          "id": "Лукойл_1",
          "taskName": "промывка фреонопровода",
          "tCompleted": false,
          "createDate": "01.03.2019",
          "completeDate": "13.03.2019",
          "factDate": "07.03.2019",
          "respPerson": "Шавлюга А.В."
        },
        {
          "id": "Лукойл_2",
          "taskName": "мотаж новой VRF-системы",
          "tCompleted": false,
          "createDate": "01.03.2019",
          "completeDate": "11.03.2019",
          "factDate": "07.03.2019",
          "respPerson": "Мороз В.А."
        },
        {
          "id": "Лукойл_3",
          "taskName": "пуско-наладка VRF-системы",
          "tCompleted": false,
          "createDate": "01.03.2019",
          "completeDate": "11.03.2019",
          "factDate": "07.03.2019",
          "respPerson": "Мороз В.А."
        },
        {
          "id": "Лукойл_4",
          "taskName": "демонтаж существующей VRF-системы",
          "tCompleted": false,
          "createDate": "01.03.2019",
          "completeDate": "13.03.2019",
          "factDate": "07.03.2019",
          "respPerson": "Шавлюга А.В."
        },
        {
          "id": "Лукойл_5",
          "taskName": "промывка фреонопровода",
          "tCompleted": false,
          "createDate": "01.03.2019",
          "completeDate": "13.03.2019",
          "factDate": "07.03.2019",
          "respPerson": "Шавлюга А.В."
        },
        {
          "id": "Лукойл_6",
          "taskName": "мотаж новой VRF-системы",
          "tCompleted": false,
          "createDate": "01.03.2019",
          "completeDate": "11.03.2019",
          "factDate": "07.03.2019",
          "respPerson": "Мороз В.А."
        },
        {
          "id": "Лукойл_7",
          "taskName": "пуско-наладка VRF-системы",
          "tCompleted": false,
          "createDate": "01.03.2019",
          "completeDate": "11.03.2019",
          "factDate": "07.03.2019",
          "respPerson": "Мороз В.А."
        },
        {
          "id": "Лукойл_8",
          "taskName": "демонтаж существующей VRF-системы",
          "tCompleted": false,
          "createDate": "01.03.2019",
          "completeDate": "13.03.2019",
          "factDate": "07.03.2019",
          "respPerson": "Шавлюга А.В."
        },
        {
          "id": "Лукойл_9",
          "taskName": "промывка фреонопровода",
          "tCompleted": false,
          "createDate": "01.03.2019",
          "completeDate": "13.03.2019",
          "factDate": "07.03.2019",
          "respPerson": "Шавлюга А.В."
        },
        {
          "id": "Лукойл_10",
          "taskName": "мотаж новой VRF-системы",
          "tCompleted": false,
          "createDate": "01.03.2019",
          "completeDate": "11.03.2019",
          "factDate": "07.03.2019",
          "respPerson": "Мороз В.А."
        },
        {
          "id": "Лукойл_11",
          "taskName": "пуско-наладка VRF-системы",
          "tCompleted": false,
          "createDate": "01.03.2019",
          "completeDate": "11.03.2019",
          "factDate": "10.05.2019",
          "respPerson": "Мороз В.А."
        }
      ]
    },
    {
      "id": "Корпорация М8",
      "projectName": "Корпорация М8",
      "pCompleted": false,
      "projectTasks": [
        {
          "id": "Корпорация М8_0",
          "taskName": "расчет и подбор приточно-вытяжной установки",
          "tCompleted": false,
          "createDate": "01.03.2019",
          "completeDate": "12.03.2019",
          "factDate": "",
          "respPerson": "Мороз В.А."
        },
        {
          "id": "Корпорация М8_1",
          "taskName": "поставка и монтаж ПВУ с рекуперацией тепла",
          "tCompleted": false,
          "createDate": "01.03.2019",
          "completeDate": "17.03.2019",
          "factDate": "",
          "respPerson": "Мороз В.А."
        },
        {
          "id": "Корпорация М8_2",
          "taskName": "прокладка воздуховодов от ПВУ",
          "tCompleted": false,
          "createDate": "01.03.2019",
          "completeDate": "18.03.2019",
          "factDate": "",
          "respPerson": "Шишков Р.В."
        },
        {
          "id": "Корпорация М8_3",
          "taskName": "пуско-наладка от ПВУ",
          "tCompleted": false,
          "createDate": "01.03.2019",
          "completeDate": "19.03.2019",
          "factDate": "",
          "respPerson": "Шишков Р.В."
        },
        {
          "id": "Корпорация М8_4",
          "taskName": "расчет и подбор систем кондиционирования",
          "tCompleted": false,
          "createDate": "01.03.2019",
          "completeDate": "20.03.2019",
          "factDate": "",
          "respPerson": "Гриневский А.С."
        },
        {
          "id": "Корпорация М8_5",
          "taskName": "поставка и монтаж систем кондиционирования",
          "tCompleted": false,
          "createDate": "01.03.2019",
          "completeDate": "12.03.2019",
          "factDate": "",
          "respPerson": "Шишков Р.В."
        },
        {
          "id": "Корпорация М8_6",
          "taskName": "пуско-наладка систем кондиционирования",
          "tCompleted": false,
          "createDate": "01.03.2019",
          "completeDate": "15.03.2019",
          "factDate": "",
          "respPerson": "Гриневский А.С."
        },
        {
          "id": "Корпорация М8_7",
          "taskName": "расчет и подбор приточно-вытяжной установки",
          "tCompleted": false,
          "createDate": "01.03.2019",
          "completeDate": "12.03.2019",
          "factDate": "",
          "respPerson": "Мороз В.А."
        },
        {
          "id": "Корпорация М8_8",
          "taskName": "поставка и монтаж ПВУ с рекуперацией тепла",
          "tCompleted": false,
          "createDate": "01.03.2019",
          "completeDate": "17.03.2019",
          "factDate": "",
          "respPerson": "Мороз В.А."
        },
        {
          "id": "Корпорация М8_9",
          "taskName": "прокладка воздуховодов от ПВУ",
          "tCompleted": false,
          "createDate": "01.03.2019",
          "completeDate": "18.03.2019",
          "factDate": "",
          "respPerson": "Шишков Р.В."
        },
        {
          "id": "Корпорация М8_10",
          "taskName": "пуско-наладка от ПВУ",
          "tCompleted": false,
          "createDate": "01.03.2019",
          "completeDate": "19.03.2019",
          "factDate": "",
          "respPerson": "Шишков Р.В."
        },
        {
          "id": "Корпорация М8_11",
          "taskName": "расчет и подбор систем кондиционирования",
          "tCompleted": false,
          "createDate": "01.03.2019",
          "completeDate": "20.03.2019",
          "factDate": "",
          "respPerson": "Гриневский А.С."
        },
        {
          "id": "Корпорация М8_12",
          "taskName": "поставка и монтаж систем кондиционирования",
          "tCompleted": false,
          "createDate": "01.03.2019",
          "completeDate": "12.03.2019",
          "factDate": "",
          "respPerson": "Шишков Р.В."
        },
        {
          "id": "Корпорация М8_13",
          "taskName": "пуско-наладка систем кондиционирования",
          "tCompleted": false,
          "createDate": "01.03.2019",
          "completeDate": "15.03.2019",
          "factDate": "",
          "respPerson": "Гриневский А.С."
        }
      ]
    },
    {
      "id": "Энергосбыт",
      "projectName": "Энергосбыт",
      "pCompleted": false,
      "projectTasks": [
        {
          "id": "Энергосбыт_0",
          "taskName": "определение количества устаревших кондиционеров",
          "tCompleted": false,
          "createDate": "01.03.2019",
          "completeDate": "16.03.2019",
          "factDate": "",
          "respPerson": "Шавлюга А.В."
        },
        {
          "id": "Энергосбыт_1",
          "taskName": "демонтаж устаревших кондиционеров",
          "tCompleted": false,
          "createDate": "01.03.2019",
          "completeDate": "11.03.2019",
          "factDate": "",
          "respPerson": "Шавлюга А.В."
        },
        {
          "id": "Энергосбыт_2",
          "taskName": "промывка фреонопроводов",
          "tCompleted": false,
          "createDate": "01.03.2019",
          "completeDate": "11.03.2019",
          "factDate": "",
          "respPerson": "Шишков Р.В."
        },
        {
          "id": "Энергосбыт_3",
          "taskName": "поставка и монтаж новых кондиционеров на место демонтированных",
          "tCompleted": false,
          "createDate": "01.03.2019",
          "completeDate": "17.03.2019",
          "factDate": "",
          "respPerson": "Шишков Р.В."
        },
        {
          "id": "Энергосбыт_4",
          "taskName": "пуско-наладка новых кондиционеров",
          "tCompleted": false,
          "createDate": "01.03.2019",
          "completeDate": "12.03.2019",
          "factDate": "",
          "respPerson": "Мороз В.А."
        },
        {
          "id": "Энергосбыт_5",
          "taskName": "техническое обслуживание оставшихся кондиционеров",
          "tCompleted": false,
          "createDate": "01.03.2019",
          "completeDate": "13.03.2019",
          "factDate": "",
          "respPerson": "Гриневский А.С."
        },
        {
          "id": "Энергосбыт_6",
          "taskName": "определение количества устаревших кондиционеров",
          "tCompleted": false,
          "createDate": "01.03.2019",
          "completeDate": "16.03.2019",
          "factDate": "",
          "respPerson": "Шавлюга А.В."
        },
        {
          "id": "Энергосбыт_7",
          "taskName": "демонтаж устаревших кондиционеров",
          "tCompleted": false,
          "createDate": "01.03.2019",
          "completeDate": "11.03.2019",
          "factDate": "",
          "respPerson": "Шавлюга А.В."
        },
        {
          "id": "Энергосбыт_8",
          "taskName": "промывка фреонопроводов",
          "tCompleted": false,
          "createDate": "01.03.2019",
          "completeDate": "11.03.2019",
          "factDate": "",
          "respPerson": "Шишков Р.В."
        },
        {
          "id": "Энергосбыт_9",
          "taskName": "поставка и монтаж новых кондиционеров на место демонтированных",
          "tCompleted": false,
          "createDate": "01.03.2019",
          "completeDate": "17.03.2019",
          "factDate": "",
          "respPerson": "Шишков Р.В."
        },
        {
          "id": "Энергосбыт_10",
          "taskName": "пуско-наладка новых кондиционеров",
          "tCompleted": false,
          "createDate": "01.03.2019",
          "completeDate": "12.03.2019",
          "factDate": "",
          "respPerson": "Мороз В.А."
        },
        {
          "id": "Энергосбыт_11",
          "taskName": "техническое обслуживание оставшихся кондиционеров",
          "tCompleted": false,
          "createDate": "01.03.2019",
          "completeDate": "13.03.2019",
          "factDate": "",
          "respPerson": "Гриневский А.С."
        },
        {
          "id": "Энергосбыт_12",
          "taskName": "определение количества устаревших кондиционеров",
          "tCompleted": false,
          "createDate": "01.03.2019",
          "completeDate": "16.03.2019",
          "factDate": "",
          "respPerson": "Шавлюга А.В."
        },
        {
          "id": "Энергосбыт_13",
          "taskName": "демонтаж устаревших кондиционеров",
          "tCompleted": false,
          "createDate": "01.03.2019",
          "completeDate": "11.03.2019",
          "factDate": "",
          "respPerson": "Шавлюга А.В."
        },
        {
          "id": "Энергосбыт_14",
          "taskName": "промывка фреонопроводов",
          "tCompleted": false,
          "createDate": "01.03.2019",
          "completeDate": "11.03.2019",
          "factDate": "",
          "respPerson": "Шишков Р.В."
        },
        {
          "id": "Энергосбыт_15",
          "taskName": "поставка и монтаж новых кондиционеров на место демонтированных",
          "tCompleted": false,
          "createDate": "01.03.2019",
          "completeDate": "17.03.2019",
          "factDate": "",
          "respPerson": "Шишков Р.В."
        },
        {
          "id": "Энергосбыт_16",
          "taskName": "пуско-наладка новых кондиционеров",
          "tCompleted": false,
          "createDate": "01.03.2019",
          "completeDate": "12.03.2019",
          "factDate": "",
          "respPerson": "Мороз В.А."
        },
        {
          "id": "Энергосбыт_17",
          "taskName": "техническое обслуживание оставшихся кондиционеров",
          "tCompleted": true,
          "createDate": "01.03.2019",
          "completeDate": "13.03.2019",
          "factDate": "09.03.2019",
          "respPerson": "Гриневский А.С."
        }
      ]
    }
  ],
  "calendar": [
    31,
    28,
    31,
    30,
    31,
    30,
    31,
    31,
    30,
    31,
    30,
    31
  ]
}